aiosatisfactory/__init__.py
aiosatisfactory/https/__init__.py
aiosatisfactory/https/api.py
aiosatisfactory/https/models.py
aiosatisfactory/lightweight/__init__.py
aiosatisfactory/lightweight/const.py
aiosatisfactory/lightweight/request.py
aiosatisfactory/lightweight/response.py
aiosatisfactory/lightweight/udp.py
aiosatisfactory-0.1.2.dist-info/licenses/LICENSE
aiosatisfactory-0.1.2.dist-info/METADATA
aiosatisfactory-0.1.2.dist-info/WHEEL
aiosatisfactory-0.1.2.dist-info/top_level.txt
aiosatisfactory-0.1.2.dist-info/RECORD
