Metadata-Version: 2.4
Name: aiosatisfactory
Version: 0.1.2
Summary: Async client for Satisfactory dedicated server APIs
Author: Rikys
License-Expression: MIT
Project-URL: Homepage, https://github.com/Rikys/aiosatisfactory
Project-URL: Documentation, https://github.com/Rikys/aiosatisfactory#readme
Project-URL: Issues, https://github.com/Rikys/aiosatisfactory/issues
Requires-Python: >=3.10
License-File: LICENSE
Requires-Dist: aiohttp>=3.9.0
Dynamic: license-file
